scrng/__init__.py
scrng/main.py
scrng-1.0.0.2024.dist-info/LICENSE
scrng-1.0.0.2024.dist-info/METADATA
scrng-1.0.0.2024.dist-info/WHEEL
scrng-1.0.0.2024.dist-info/top_level.txt
scrng-1.0.0.2024.dist-info/RECORD
