Metadata-Version: 2.1
Name: scrng
Version: 1.0.0.2024
Summary: A utility for generating random digits.
Author-email: Rohan Date <rohan.s.date@icloud.com>
Classifier: Programming Language :: Python :: 3
Classifier: License :: OSI Approved :: MIT License
Classifier: Operating System :: OS Independent
Classifier: Development Status :: 5 - Production/Stable
Requires-Python: >=3.11
License-File: LICENSE
